liblaf/apple/__init__.py
liblaf/apple/__init__.pyi
liblaf/apple/_version.py
liblaf/apple/_version.pyi
liblaf/apple/py.typed
liblaf/apple/constants/__init__.py
liblaf/apple/constants/__init__.pyi
liblaf/apple/constants/_array_names.py
liblaf/apple/inverse/__init__.py
liblaf/apple/inverse/__init__.pyi
liblaf/apple/inverse/_inverse.py
liblaf/apple/inverse/_types.py
liblaf/apple/jax/__init__.py
liblaf/apple/jax/__init__.pyi
liblaf/apple/jax/energies/__init__.py
liblaf/apple/jax/energies/__init__.pyi
liblaf/apple/jax/energies/_gravity.py
liblaf/apple/jax/energies/_mass_spring.py
liblaf/apple/jax/energies/_mass_spring_prestrain.py
liblaf/apple/jax/fem/__init__.py
liblaf/apple/jax/fem/__init__.pyi
liblaf/apple/jax/fem/element/__init__.py
liblaf/apple/jax/fem/element/__init__.pyi
liblaf/apple/jax/fem/element/_element.py
liblaf/apple/jax/fem/element/_tetra.py
liblaf/apple/jax/fem/geometry/__init__.py
liblaf/apple/jax/fem/geometry/__init__.pyi
liblaf/apple/jax/fem/geometry/_geometry.py
liblaf/apple/jax/fem/geometry/_tetra.py
liblaf/apple/jax/fem/geometry/_triangle.py
liblaf/apple/jax/fem/quadrature/__init__.py
liblaf/apple/jax/fem/quadrature/__init__.pyi
liblaf/apple/jax/fem/quadrature/_scheme.py
liblaf/apple/jax/fem/quadrature/_tetra.py
liblaf/apple/jax/fem/region/__init__.py
liblaf/apple/jax/fem/region/__init__.pyi
liblaf/apple/jax/fem/region/_region.py
liblaf/apple/jax/math/__init__.py
liblaf/apple/jax/math/__init__.pyi
liblaf/apple/jax/math/_normalize.py
liblaf/apple/jax/model/__init__.py
liblaf/apple/jax/model/__init__.pyi
liblaf/apple/jax/model/_builder.py
liblaf/apple/jax/model/_energy.py
liblaf/apple/jax/model/_model.py
liblaf/apple/jax/model/dirichlet/__init__.py
liblaf/apple/jax/model/dirichlet/__init__.pyi
liblaf/apple/jax/model/dirichlet/_builder.py
liblaf/apple/jax/model/dirichlet/_dirichlet.py
liblaf/apple/jax/testing/__init__.py
liblaf/apple/jax/testing/__init__.pyi
liblaf/apple/jax/testing/_close.py
liblaf/apple/jax/testing/_jvp.py
liblaf_apple-0.7.0.dist-info/METADATA
liblaf_apple-0.7.0.dist-info/WHEEL
liblaf_apple-0.7.0.dist-info/licenses/LICENSE
liblaf_apple-0.7.0.dist-info/RECORD
