Metadata-Version: 2.4
Name: liblaf-apple
Version: 0.7.0
Summary: 🍎 A JAX and Warp library for differentiable physics simulation, featuring elastic energy models and finite element methods.
Project-URL: Changelog, https://github.com/liblaf/apple/blob/main/CHANGELOG.md
Project-URL: Documentation, https://liblaf-apple.readthedocs.io/
Project-URL: Homepage, https://github.com/liblaf/apple
Project-URL: Issue Tracker, https://github.com/liblaf/apple/issues
Project-URL: Release Notes, https://github.com/liblaf/apple/releases
Project-URL: Source Code, https://github.com/liblaf/apple
Author-email: liblaf <30631553+liblaf@users.noreply.github.com>
License-Expression: MIT
License-File: LICENSE
Classifier: Development Status :: 4 - Beta
Classifier: Intended Audience :: Developers
Classifier: License :: OSI Approved
Classifier: License :: OSI Approved :: MIT License
Classifier: Operating System :: OS Independent
Classifier: Programming Language :: Python
Classifier: Programming Language :: Python :: 3
Classifier: Programming Language :: Python :: 3.12
Classifier: Programming Language :: Python :: 3.13
Classifier: Typing :: Typed
Requires-Python: >=3.12
Requires-Dist: beartype<0.23,>=0.22
Requires-Dist: cytoolz<2,>=1
Requires-Dist: einops<0.9,>=0.8
Requires-Dist: equinox<0.14,>=0.13
Requires-Dist: felupe<10,>=9
Requires-Dist: jax<0.9,>=0.8
Requires-Dist: jaxtyping<0.4,>=0.3
Requires-Dist: lazy-loader<0.5,>=0.4
Requires-Dist: liblaf-grapes<9,>=8
Requires-Dist: liblaf-melon<0.10,>=0.9
Requires-Dist: liblaf-peach<0.8,>=0.7
Requires-Dist: lineax<0.0.9,>=0.0.8
Requires-Dist: loguru<0.8,>=0.7
Requires-Dist: matplotlib<4,>=3
Requires-Dist: numpy<3,>=2
Requires-Dist: optax<0.3,>=0.2
Requires-Dist: pyvista<0.47,>=0.46
Requires-Dist: rich<15,>=14
Requires-Dist: scipy<2,>=1
Requires-Dist: warp-lang<2,>=1
